<?xml version="1.0" encoding="utf-8"?><GetCompetitionStatisticsByMatchResponse xmlns:i="http://www.w3.org/2001/XMLSchema-instance" xmlns="http://DHSBusinessService.Operations"><ResponseStatus xmlns:d2p1="http://schemas.servicestack.net/types"><d2p1:ErrorCode i:nil="true" /><d2p1:Message i:nil="true" /><d2p1:StackTrace i:nil="true" /><d2p1:Errors i:nil="true" /><d2p1:Meta xmlns:d3p1="http://schemas.microsoft.com/2003/10/Serialization/Arrays"><d3p1:KeyValueOfstringstring><d3p1:Key>OperationId</d3p1:Key><d3p1:Value>913b0ee2-9c5b-4599-8c6a-20c54f7de4e6</d3p1:Value></d3p1:KeyValueOfstringstring></d2p1:Meta></ResponseStatus><CompetitionStatistics xmlns:d2p1="http://schemas.datacontract.org/2004/07/Deltatre.DigitalMedia.APIs.FIFA.DTO.Stats"><d2p1:Competition i:nil="true" /><d2p1:CompetitionTypeId>17</d2p1:CompetitionTypeId><d2p1:MatchStats /><d2p1:PlayerStats><d2p1:PlayerStatsDto><d2p1:ClubShirtName>VALLADARES</d2p1:ClubShirtName><d2p1:CommonName>Noel VALLADARES</d2p1:CommonName><d2p1:PlayerID>178185</d2p1:PlayerID><d2p1:PlayerOfficialName>Noel</d2p1:PlayerOfficialName><d2p1:PlayerOfficialSurname>VALLADARES</d2p1:PlayerOfficialSurname><d2p1:ShortName>VALLADARES</d2p1:ShortName><d2p1:StatsValues><d2p1:StatsItemDto><d2p1:CumulativePhase>0</d2p1:CumulativePhase><d2p1:Rank>445</d2p1:Rank><d2p1:StatsID>27</d2p1:StatsID><d2p1:ValueDecimal>10028.0000</d2p1:ValueDecimal><d2p1:ValueString>10028</d2p1:ValueString></d2p1:StatsItemDto></d2p1:StatsValues><d2p1:TeamID>43909</d2p1:TeamID></d2p1:PlayerStatsDto><d2p1:PlayerStatsDto><d2p1:ClubShirtName>W. PALACIOS</d2p1:ClubShirtName><d2p1:CommonName>Wilson PALACIOS</d2p1:CommonName><d2p1:PlayerID>209827</d2p1:PlayerID><d2p1:PlayerOfficialName>Wilson</d2p1:PlayerOfficialName><d2p1:PlayerOfficialSurname>PALACIOS</d2p1:PlayerOfficialSurname><d2p1:ShortName>W. PALACIOS</d2p1:ShortName><d2p1:StatsValues><d2p1:StatsItemDto><d2p1:CumulativePhase>0</d2p1:CumulativePhase><d2p1:Rank>406</d2p1:Rank><d2p1:StatsID>27</d2p1:StatsID><d2p1:ValueDecimal>12541.0000</d2p1:ValueDecimal><d2p1:ValueString>12541</d2p1:ValueString></d2p1:StatsItemDto></d2p1:StatsValues><d2p1:TeamID>43909</d2p1:TeamID></d2p1:PlayerStatsDto><d2p1:PlayerStatsDto><d2p1:ClubShirtName>EVRA</d2p1:ClubShirtName><d2p1:CommonName>Patrice EVRA</d2p1:CommonName><d2p1:PlayerID>212246</d2p1:PlayerID><d2p1:PlayerOfficialName>Patrice</d2p1:PlayerOfficialName><d2p1:PlayerOfficialSurname>EVRA</d2p1:PlayerOfficialSurname><d2p1:ShortName>EVRA</d2p1:ShortName><d2p1:StatsValues><d2p1:StatsItemDto><d2p1:CumulativePhase>0</d2p1:CumulativePhase><d2p1:Rank>121</d2p1:Rank><d2p1:StatsID>27</d2p1:StatsID><d2p1:ValueDecimal>36263.0000</d2p1:ValueDecimal><d2p1:ValueString>36263</d2p1:ValueString></d2p1:StatsItemDto></d2p1:StatsValues><d2p1:TeamID>43946</d2p1:TeamID></d2p1:PlayerStatsDto><d2p1:PlayerStatsDto><d2p1:ClubShirtName>BERNARDEZ</d2p1:ClubShirtName><d2p1:CommonName>Victor BERNARDEZ</d2p1:CommonName><d2p1:PlayerID>213878</d2p1:PlayerID><d2p1:PlayerOfficialName>Victor</d2p1:PlayerOfficialName><d2p1:PlayerOfficialSurname>BERNARDEZ</d2p1:PlayerOfficialSurname><d2p1:ShortName>BERNARDEZ</d2p1:ShortName><d2p1:StatsValues><d2p1:StatsItemDto><d2p1:CumulativePhase>0</d2p1:CumulativePhase><d2p1:Rank>316</d2p1:Rank><d2p1:StatsID>27</d2p1:StatsID><d2p1:ValueDecimal>20114.0000</d2p1:ValueDecimal><d2p1:ValueString>20114</d2p1:ValueString></d2p1:StatsItemDto></d2p1:StatsValues><d2p1:TeamID>43909</d2p1:TeamID></d2p1:PlayerStatsDto><d2p1:PlayerStatsDto><d2p1:ClubShirtName>FIGUEROA</d2p1:ClubShirtName><d2p1:CommonName>Maynor FIGUEROA</d2p1:CommonName><d2p1:PlayerID>213879</d2p1:PlayerID><d2p1:PlayerOfficialName>Maynor</d2p1:PlayerOfficialName><d2p1:PlayerOfficialSurname>FIGUEROA</d2p1:PlayerOfficialSurname><d2p1:ShortName>FIGUEROA</d2p1:ShortName><d2p1:StatsValues><d2p1:StatsItemDto><d2p1:CumulativePhase>0</d2p1:CumulativePhase><d2p1:Rank>240</d2p1:Rank><d2p1:StatsID>27</d2p1:StatsID><d2p1:ValueDecimal>26303.0000</d2p1:ValueDecimal><d2p1:ValueString>26303</d2p1:ValueString></d2p1:StatsItemDto></d2p1:StatsValues><d2p1:TeamID>43909</d2p1:TeamID></d2p1:PlayerStatsDto><d2p1:PlayerStatsDto><d2p1:ClubShirtName>J. PALACIOS</d2p1:ClubShirtName><d2p1:CommonName>Jerry PALACIOS</d2p1:CommonName><d2p1:PlayerID>213953</d2p1:PlayerID><d2p1:PlayerOfficialName>Jerry</d2p1:PlayerOfficialName><d2p1:PlayerOfficialSurname>PALACIOS</d2p1:PlayerOfficialSurname><d2p1:ShortName>J. PALACIOS</d2p1:ShortName><d2p1:StatsValues><d2p1:StatsItemDto><d2p1:CumulativePhase>0</d2p1:CumulativePhase><d2p1:Rank>523</d2p1:Rank><d2p1:StatsID>27</d2p1:StatsID><d2p1:ValueDecimal>5669.0000</d2p1:ValueDecimal><d2p1:ValueString>5669</d2p1:ValueString></d2p1:StatsItemDto></d2p1:StatsValues><d2p1:TeamID>43909</d2p1:TeamID></d2p1:PlayerStatsDto><d2p1:PlayerStatsDto><d2p1:ClubShirtName>MAVUBA</d2p1:ClubShirtName><d2p1:CommonName>Antonio MAVUBA</d2p1:CommonName><d2p1:PlayerID>214571</d2p1:PlayerID><d2p1:PlayerOfficialName>Antonio</d2p1:PlayerOfficialName><d2p1:PlayerOfficialSurname>MAVUBA</d2p1:PlayerOfficialSurname><d2p1:ShortName>MAVUBA</d2p1:ShortName><d2p1:StatsValues><d2p1:StatsItemDto><d2p1:CumulativePhase>0</d2p1:CumulativePhase><d2p1:Rank>560</d2p1:Rank><d2p1:StatsID>27</d2p1:StatsID><d2p1:ValueDecimal>3257.0000</d2p1:ValueDecimal><d2p1:ValueString>3257</d2p1:ValueString></d2p1:StatsItemDto></d2p1:StatsValues><d2p1:TeamID>43946</d2p1:TeamID></d2p1:PlayerStatsDto><d2p1:PlayerStatsDto><d2p1:ClubShirtName>M. CHAVEZ</d2p1:ClubShirtName><d2p1:CommonName>Marvin CHAVEZ</d2p1:CommonName><d2p1:PlayerID>227839</d2p1:PlayerID><d2p1:PlayerOfficialName>Marvin</d2p1:PlayerOfficialName><d2p1:PlayerOfficialSurname>CHAVEZ</d2p1:PlayerOfficialSurname><d2p1:ShortName>M. CHAVEZ</d2p1:ShortName><d2p1:StatsValues><d2p1:StatsItemDto><d2p1:CumulativePhase>0</d2p1:CumulativePhase><d2p1:Rank>528</d2p1:Rank><d2p1:StatsID>27</d2p1:StatsID><d2p1:ValueDecimal>5455.0000</d2p1:ValueDecimal><d2p1:ValueString>5455</d2p1:ValueString></d2p1:StatsItemDto></d2p1:StatsValues><d2p1:TeamID>43909</d2p1:TeamID></d2p1:PlayerStatsDto><d2p1:PlayerStatsDto><d2p1:ClubShirtName>CLAROS</d2p1:ClubShirtName><d2p1:CommonName>Jorge CLAROS</d2p1:CommonName><d2p1:PlayerID>230114</d2p1:PlayerID><d2p1:PlayerOfficialName>Jorge</d2p1:PlayerOfficialName><d2p1:PlayerOfficialSurname>CLAROS</d2p1:PlayerOfficialSurname><d2p1:ShortName>CLAROS</d2p1:ShortName><d2p1:StatsValues><d2p1:StatsItemDto><d2p1:CumulativePhase>0</d2p1:CumulativePhase><d2p1:Rank>268</d2p1:Rank><d2p1:StatsID>27</d2p1:StatsID><d2p1:ValueDecimal>23940.0000</d2p1:ValueDecimal><d2p1:ValueString>23940</d2p1:ValueString></d2p1:StatsItemDto></d2p1:StatsValues><d2p1:TeamID>43909</d2p1:TeamID></d2p1:PlayerStatsDto><d2p1:PlayerStatsDto><d2p1:ClubShirtName>EMILIO</d2p1:ClubShirtName><d2p1:CommonName>Emilio IZAGUIRRE</d2p1:CommonName><d2p1:PlayerID>230117</d2p1:PlayerID><d2p1:PlayerOfficialName>Emilio</d2p1:PlayerOfficialName><d2p1:PlayerOfficialSurname>IZAGUIRRE</d2p1:PlayerOfficialSurname><d2p1:ShortName>IZAGUIRRE</d2p1:ShortName><d2p1:StatsValues><d2p1:StatsItemDto><d2p1:CumulativePhase>0</d2p1:CumulativePhase><d2p1:Rank>387</d2p1:Rank><d2p1:StatsID>27</d2p1:StatsID><d2p1:ValueDecimal>13921.0000</d2p1:ValueDecimal><d2p1:ValueString>13921</d2p1:ValueString></d2p1:StatsItemDto></d2p1:StatsValues><d2p1:TeamID>43909</d2p1:TeamID></d2p1:PlayerStatsDto><d2p1:PlayerStatsDto><d2p1:ClubShirtName>BONIEK</d2p1:ClubShirtName><d2p1:CommonName>Boniek GARCIA</d2p1:CommonName><d2p1:PlayerID>237071</d2p1:PlayerID><d2p1:PlayerOfficialName>Boniek</d2p1:PlayerOfficialName><d2p1:PlayerOfficialSurname>GARCIA</d2p1:PlayerOfficialSurname><d2p1:ShortName>B. GARCIA</d2p1:ShortName><d2p1:StatsValues><d2p1:StatsItemDto><d2p1:CumulativePhase>0</d2p1:CumulativePhase><d2p1:Rank>296</d2p1:Rank><d2p1:StatsID>27</d2p1:StatsID><d2p1:ValueDecimal>21363.0000</d2p1:ValueDecimal><d2p1:ValueString>21363</d2p1:ValueString></d2p1:StatsItemDto></d2p1:StatsValues><d2p1:TeamID>43909</d2p1:TeamID></d2p1:PlayerStatsDto><d2p1:PlayerStatsDto><d2p1:ClubShirtName>SAGNA</d2p1:ClubShirtName><d2p1:CommonName>Bacary SAGNA</d2p1:CommonName><d2p1:PlayerID>254141</d2p1:PlayerID><d2p1:PlayerOfficialName>Bacary</d2p1:PlayerOfficialName><d2p1:PlayerOfficialSurname>SAGNA</d2p1:PlayerOfficialSurname><d2p1:ShortName>SAGNA</d2p1:ShortName><d2p1:StatsValues><d2p1:StatsItemDto><d2p1:CumulativePhase>0</d2p1:CumulativePhase><d2p1:Rank>437</d2p1:Rank><d2p1:StatsID>27</d2p1:StatsID><d2p1:ValueDecimal>10381.0000</d2p1:ValueDecimal><d2p1:ValueString>10381</d2p1:ValueString></d2p1:StatsItemDto></d2p1:StatsValues><d2p1:TeamID>43946</d2p1:TeamID></d2p1:PlayerStatsDto><d2p1:PlayerStatsDto><d2p1:ClubShirtName>GARRIDO</d2p1:ClubShirtName><d2p1:CommonName>Luis GARRIDO</d2p1:CommonName><d2p1:PlayerID>270400</d2p1:PlayerID><d2p1:PlayerOfficialName>Luis</d2p1:PlayerOfficialName><d2p1:PlayerOfficialSurname>GARRIDO</d2p1:PlayerOfficialSurname><d2p1:ShortName>GARRIDO</d2p1:ShortName><d2p1:StatsValues><d2p1:StatsItemDto><d2p1:CumulativePhase>0</d2p1:CumulativePhase><d2p1:Rank>315</d2p1:Rank><d2p1:StatsID>27</d2p1:StatsID><d2p1:ValueDecimal>20125.0000</d2p1:ValueDecimal><d2p1:ValueString>20125</d2p1:ValueString></d2p1:StatsItemDto></d2p1:StatsValues><d2p1:TeamID>43909</d2p1:TeamID></d2p1:PlayerStatsDto><d2p1:PlayerStatsDto><d2p1:ClubShirtName>COSTLY</d2p1:ClubShirtName><d2p1:CommonName>Carlo COSTLY</d2p1:CommonName><d2p1:PlayerID>271414</d2p1:PlayerID><d2p1:PlayerOfficialName>Carlo</d2p1:PlayerOfficialName><d2p1:PlayerOfficialSurname>COSTLY</d2p1:PlayerOfficialSurname><d2p1:ShortName>COSTLY</d2p1:ShortName><d2p1:StatsValues><d2p1:StatsItemDto><d2p1:CumulativePhase>0</d2p1:CumulativePhase><d2p1:Rank>286</d2p1:Rank><d2p1:StatsID>27</d2p1:StatsID><d2p1:ValueDecimal>22272.0000</d2p1:ValueDecimal><d2p1:ValueString>22272</d2p1:ValueString></d2p1:StatsItemDto></d2p1:StatsValues><d2p1:TeamID>43909</d2p1:TeamID></d2p1:PlayerStatsDto><d2p1:PlayerStatsDto><d2p1:ClubShirtName>SAKHO</d2p1:ClubShirtName><d2p1:CommonName>SAKHO</d2p1:CommonName><d2p1:PlayerID>274135</d2p1:PlayerID><d2p1:PlayerOfficialName>Mamadou</d2p1:PlayerOfficialName><d2p1:PlayerOfficialSurname>SAKHO</d2p1:PlayerOfficialSurname><d2p1:ShortName>SAKHO</d2p1:ShortName><d2p1:StatsValues><d2p1:StatsItemDto><d2p1:CumulativePhase>0</d2p1:CumulativePhase><d2p1:Rank>222</d2p1:Rank><d2p1:StatsID>27</d2p1:StatsID><d2p1:ValueDecimal>27961.0000</d2p1:ValueDecimal><d2p1:ValueString>27961</d2p1:ValueString></d2p1:StatsItemDto></d2p1:StatsValues><d2p1:TeamID>43946</d2p1:TeamID></d2p1:PlayerStatsDto><d2p1:PlayerStatsDto><d2p1:ClubShirtName>M. MARTINEZ</d2p1:ClubShirtName><d2p1:CommonName>Mario MARTINEZ</d2p1:CommonName><d2p1:PlayerID>296297</d2p1:PlayerID><d2p1:PlayerOfficialName>Mario</d2p1:PlayerOfficialName><d2p1:PlayerOfficialSurname>MARTINEZ</d2p1:PlayerOfficialSurname><d2p1:ShortName>M. MARTINEZ</d2p1:ShortName><d2p1:StatsValues><d2p1:StatsItemDto><d2p1:CumulativePhase>0</d2p1:CumulativePhase><d2p1:Rank>578</d2p1:Rank><d2p1:StatsID>27</d2p1:StatsID><d2p1:ValueDecimal>2182.0000</d2p1:ValueDecimal><d2p1:ValueString>2182</d2p1:ValueString></d2p1:StatsItemDto></d2p1:StatsValues><d2p1:TeamID>43909</d2p1:TeamID></d2p1:PlayerStatsDto><d2p1:PlayerStatsDto><d2p1:ClubShirtName>J.C. GARCIA</d2p1:ClubShirtName><d2p1:CommonName>Juan Carlos GARCIA</d2p1:CommonName><d2p1:PlayerID>296303</d2p1:PlayerID><d2p1:PlayerOfficialName>Juan Carlos</d2p1:PlayerOfficialName><d2p1:PlayerOfficialSurname>GARCIA</d2p1:PlayerOfficialSurname><d2p1:ShortName>J. C. GARCIA</d2p1:ShortName><d2p1:StatsValues><d2p1:StatsItemDto><d2p1:CumulativePhase>0</d2p1:CumulativePhase><d2p1:Rank>388</d2p1:Rank><d2p1:StatsID>27</d2p1:StatsID><d2p1:ValueDecimal>13909.0000</d2p1:ValueDecimal><d2p1:ValueString>13909</d2p1:ValueString></d2p1:StatsItemDto></d2p1:StatsValues><d2p1:TeamID>43909</d2p1:TeamID></d2p1:PlayerStatsDto><d2p1:PlayerStatsDto><d2p1:ClubShirtName>BENZEMA</d2p1:ClubShirtName><d2p1:CommonName>Karim BENZEMA</d2p1:CommonName><d2p1:PlayerID>297103</d2p1:PlayerID><d2p1:PlayerOfficialName>Karim</d2p1:PlayerOfficialName><d2p1:PlayerOfficialSurname>BENZEMA</d2p1:PlayerOfficialSurname><d2p1:ShortName>BENZEMA</d2p1:ShortName><d2p1:StatsValues><d2p1:StatsItemDto><d2p1:CumulativePhase>0</d2p1:CumulativePhase><d2p1:Rank>42</d2p1:Rank><d2p1:StatsID>27</d2p1:StatsID><d2p1:ValueDecimal>47379.0000</d2p1:ValueDecimal><d2p1:ValueString>47379</d2p1:ValueString></d2p1:StatsItemDto></d2p1:StatsValues><d2p1:TeamID>43946</d2p1:TeamID></d2p1:PlayerStatsDto><d2p1:PlayerStatsDto><d2p1:ClubShirtName>LLORIS</d2p1:ClubShirtName><d2p1:CommonName>LLORIS</d2p1:CommonName><d2p1:PlayerID>297105</d2p1:PlayerID><d2p1:PlayerOfficialName>Hugo</d2p1:PlayerOfficialName><d2p1:PlayerOfficialSurname>LLORIS</d2p1:PlayerOfficialSurname><d2p1:ShortName>LLORIS</d2p1:ShortName><d2p1:StatsValues><d2p1:StatsItemDto><d2p1:CumulativePhase>0</d2p1:CumulativePhase><d2p1:Rank>274</d2p1:Rank><d2p1:StatsID>27</d2p1:StatsID><d2p1:ValueDecimal>23283.0000</d2p1:ValueDecimal><d2p1:ValueString>23283</d2p1:ValueString></d2p1:StatsItemDto></d2p1:StatsValues><d2p1:TeamID>43946</d2p1:TeamID></d2p1:PlayerStatsDto><d2p1:PlayerStatsDto><d2p1:ClubShirtName>VALBUENA</d2p1:ClubShirtName><d2p1:CommonName>Mathieu VALBUENA</d2p1:CommonName><d2p1:PlayerID>297106</d2p1:PlayerID><d2p1:PlayerOfficialName>Mathieu</d2p1:PlayerOfficialName><d2p1:PlayerOfficialSurname>VALBUENA</d2p1:PlayerOfficialSurname><d2p1:ShortName>VALBUENA</d2p1:ShortName><d2p1:StatsValues><d2p1:StatsItemDto><d2p1:CumulativePhase>0</d2p1:CumulativePhase><d2p1:Rank>106</d2p1:Rank><d2p1:StatsID>27</d2p1:StatsID><d2p1:ValueDecimal>38070.0000</d2p1:ValueDecimal><d2p1:ValueString>38070</d2p1:ValueString></d2p1:StatsItemDto></d2p1:StatsValues><d2p1:TeamID>43946</d2p1:TeamID></d2p1:PlayerStatsDto><d2p1:PlayerStatsDto><d2p1:ClubShirtName>O. CHAVEZ</d2p1:ClubShirtName><d2p1:CommonName>Osman CHAVEZ</d2p1:CommonName><d2p1:PlayerID>297230</d2p1:PlayerID><d2p1:PlayerOfficialName>Osman</d2p1:PlayerOfficialName><d2p1:PlayerOfficialSurname>CHAVEZ</d2p1:PlayerOfficialSurname><d2p1:ShortName>O. CHAVEZ</d2p1:ShortName><d2p1:StatsValues><d2p1:StatsItemDto><d2p1:CumulativePhase>0</d2p1:CumulativePhase><d2p1:Rank>543</d2p1:Rank><d2p1:StatsID>27</d2p1:StatsID><d2p1:ValueDecimal>4486.0000</d2p1:ValueDecimal><d2p1:ValueString>4486</d2p1:ValueString></d2p1:StatsItemDto></d2p1:StatsValues><d2p1:TeamID>43909</d2p1:TeamID></d2p1:PlayerStatsDto><d2p1:PlayerStatsDto><d2p1:ClubShirtName>REMY</d2p1:ClubShirtName><d2p1:CommonName>Loic REMY</d2p1:CommonName><d2p1:PlayerID>299878</d2p1:PlayerID><d2p1:PlayerOfficialName>Loic</d2p1:PlayerOfficialName><d2p1:PlayerOfficialSurname>REMY</d2p1:PlayerOfficialSurname><d2p1:ShortName>REMY</d2p1:ShortName><d2p1:StatsValues><d2p1:StatsItemDto><d2p1:CumulativePhase>0</d2p1:CumulativePhase><d2p1:Rank>539</d2p1:Rank><d2p1:StatsID>27</d2p1:StatsID><d2p1:ValueDecimal>4654.0000</d2p1:ValueDecimal><d2p1:ValueString>4654</d2p1:ValueString></d2p1:StatsItemDto></d2p1:StatsValues><d2p1:TeamID>43946</d2p1:TeamID></d2p1:PlayerStatsDto><d2p1:PlayerStatsDto><d2p1:ClubShirtName>ESPINOZA</d2p1:ClubShirtName><d2p1:CommonName>Roger ESPINOZA</d2p1:CommonName><d2p1:PlayerID>304934</d2p1:PlayerID><d2p1:PlayerOfficialName>Roger</d2p1:PlayerOfficialName><d2p1:PlayerOfficialSurname>ESPINOZA</d2p1:PlayerOfficialSurname><d2p1:ShortName>ESPINOZA</d2p1:ShortName><d2p1:StatsValues><d2p1:StatsItemDto><d2p1:CumulativePhase>0</d2p1:CumulativePhase><d2p1:Rank>253</d2p1:Rank><d2p1:StatsID>27</d2p1:StatsID><d2p1:ValueDecimal>25713.0000</d2p1:ValueDecimal><d2p1:ValueString>25713</d2p1:ValueString></d2p1:StatsItemDto></d2p1:StatsValues><d2p1:TeamID>43909</d2p1:TeamID></d2p1:PlayerStatsDto><d2p1:PlayerStatsDto><d2p1:ClubShirtName>SISSOKO</d2p1:ClubShirtName><d2p1:CommonName>SISSOKO</d2p1:CommonName><d2p1:PlayerID>317056</d2p1:PlayerID><d2p1:PlayerOfficialName>Moussa</d2p1:PlayerOfficialName><d2p1:PlayerOfficialSurname>SISSOKO</d2p1:PlayerOfficialSurname><d2p1:ShortName>SISSOKO</d2p1:ShortName><d2p1:StatsValues><d2p1:StatsItemDto><d2p1:CumulativePhase>0</d2p1:CumulativePhase><d2p1:Rank>251</d2p1:Rank><d2p1:StatsID>27</d2p1:StatsID><d2p1:ValueDecimal>25844.0000</d2p1:ValueDecimal><d2p1:ValueString>25844</d2p1:ValueString></d2p1:StatsItemDto></d2p1:StatsValues><d2p1:TeamID>43946</d2p1:TeamID></d2p1:PlayerStatsDto><d2p1:PlayerStatsDto><d2p1:ClubShirtName>BENGTSON</d2p1:ClubShirtName><d2p1:CommonName>Jerry BENGTSON</d2p1:CommonName><d2p1:PlayerID>323623</d2p1:PlayerID><d2p1:PlayerOfficialName>Jerry</d2p1:PlayerOfficialName><d2p1:PlayerOfficialSurname>BENGTSON</d2p1:PlayerOfficialSurname><d2p1:ShortName>BENGTSON</d2p1:ShortName><d2p1:StatsValues><d2p1:StatsItemDto><d2p1:CumulativePhase>0</d2p1:CumulativePhase><d2p1:Rank>288</d2p1:Rank><d2p1:StatsID>27</d2p1:StatsID><d2p1:ValueDecimal>22218.0000</d2p1:ValueDecimal><d2p1:ValueString>22218</d2p1:ValueString></d2p1:StatsItemDto></d2p1:StatsValues><d2p1:TeamID>43909</d2p1:TeamID></d2p1:PlayerStatsDto><d2p1:PlayerStatsDto><d2p1:ClubShirtName>NAJAR</d2p1:ClubShirtName><d2p1:CommonName>Andy NAJAR</d2p1:CommonName><d2p1:PlayerID>330693</d2p1:PlayerID><d2p1:PlayerOfficialName>Andy</d2p1:PlayerOfficialName><d2p1:PlayerOfficialSurname>NAJAR</d2p1:PlayerOfficialSurname><d2p1:ShortName>NAJAR</d2p1:ShortName><d2p1:StatsValues><d2p1:StatsItemDto><d2p1:CumulativePhase>0</d2p1:CumulativePhase><d2p1:Rank>479</d2p1:Rank><d2p1:StatsID>27</d2p1:StatsID><d2p1:ValueDecimal>8378.0000</d2p1:ValueDecimal><d2p1:ValueString>8378</d2p1:ValueString></d2p1:StatsItemDto></d2p1:StatsValues><d2p1:TeamID>43909</d2p1:TeamID></d2p1:PlayerStatsDto><d2p1:PlayerStatsDto><d2p1:ClubShirtName>GRIEZMANN</d2p1:ClubShirtName><d2p1:CommonName>GRIEZMANN</d2p1:CommonName><d2p1:PlayerID>336435</d2p1:PlayerID><d2p1:PlayerOfficialName>Antoine</d2p1:PlayerOfficialName><d2p1:PlayerOfficialSurname>GRIEZMANN</d2p1:PlayerOfficialSurname><d2p1:ShortName>GRIEZMANN</d2p1:ShortName><d2p1:StatsValues><d2p1:StatsItemDto><d2p1:CumulativePhase>0</d2p1:CumulativePhase><d2p1:Rank>127</d2p1:Rank><d2p1:StatsID>27</d2p1:StatsID><d2p1:ValueDecimal>35638.0000</d2p1:ValueDecimal><d2p1:ValueString>35638</d2p1:ValueString></d2p1:StatsItemDto></d2p1:StatsValues><d2p1:TeamID>43946</d2p1:TeamID></d2p1:PlayerStatsDto><d2p1:PlayerStatsDto><d2p1:ClubShirtName>BECKELES</d2p1:ClubShirtName><d2p1:CommonName>Brayan BECKELES</d2p1:CommonName><d2p1:PlayerID>339551</d2p1:PlayerID><d2p1:PlayerOfficialName>Brayan</d2p1:PlayerOfficialName><d2p1:PlayerOfficialSurname>BECKELES</d2p1:PlayerOfficialSurname><d2p1:ShortName>BECKELES</d2p1:ShortName><d2p1:StatsValues><d2p1:StatsItemDto><d2p1:CumulativePhase>0</d2p1:CumulativePhase><d2p1:Rank>197</d2p1:Rank><d2p1:StatsID>27</d2p1:StatsID><d2p1:ValueDecimal>29720.0000</d2p1:ValueDecimal><d2p1:ValueString>29720</d2p1:ValueString></d2p1:StatsItemDto></d2p1:StatsValues><d2p1:TeamID>43909</d2p1:TeamID></d2p1:PlayerStatsDto><d2p1:PlayerStatsDto><d2p1:ClubShirtName>DEBUCHY</d2p1:ClubShirtName><d2p1:CommonName>DEBUCHY</d2p1:CommonName><d2p1:PlayerID>358011</d2p1:PlayerID><d2p1:PlayerOfficialName>Mathieu</d2p1:PlayerOfficialName><d2p1:PlayerOfficialSurname>DEBUCHY</d2p1:PlayerOfficialSurname><d2p1:ShortName>DEBUCHY</d2p1:ShortName><d2p1:StatsValues><d2p1:StatsItemDto><d2p1:CumulativePhase>0</d2p1:CumulativePhase><d2p1:Rank>91</d2p1:Rank><d2p1:StatsID>27</d2p1:StatsID><d2p1:ValueDecimal>39930.0000</d2p1:ValueDecimal><d2p1:ValueString>39930</d2p1:ValueString></d2p1:StatsItemDto></d2p1:StatsValues><d2p1:TeamID>43946</d2p1:TeamID></d2p1:PlayerStatsDto><d2p1:PlayerStatsDto><d2p1:ClubShirtName>KOSCIELNY</d2p1:ClubShirtName><d2p1:CommonName>Laurent KOSCIELNY</d2p1:CommonName><d2p1:PlayerID>358012</d2p1:PlayerID><d2p1:PlayerOfficialName>Laurent</d2p1:PlayerOfficialName><d2p1:PlayerOfficialSurname>KOSCIELNY</d2p1:PlayerOfficialSurname><d2p1:ShortName>KOSCIELNY</d2p1:ShortName><d2p1:StatsValues><d2p1:StatsItemDto><d2p1:CumulativePhase>0</d2p1:CumulativePhase><d2p1:Rank>280</d2p1:Rank><d2p1:StatsID>27</d2p1:StatsID><d2p1:ValueDecimal>22829.0000</d2p1:ValueDecimal><d2p1:ValueString>22829</d2p1:ValueString></d2p1:StatsItemDto></d2p1:StatsValues><d2p1:TeamID>43946</d2p1:TeamID></d2p1:PlayerStatsDto><d2p1:PlayerStatsDto><d2p1:ClubShirtName>CABAYE</d2p1:ClubShirtName><d2p1:CommonName>Yohan CABAYE</d2p1:CommonName><d2p1:PlayerID>358013</d2p1:PlayerID><d2p1:PlayerOfficialName>Yohan</d2p1:PlayerOfficialName><d2p1:PlayerOfficialSurname>CABAYE</d2p1:PlayerOfficialSurname><d2p1:ShortName>CABAYE</d2p1:ShortName><d2p1:StatsValues><d2p1:StatsItemDto><d2p1:CumulativePhase>0</d2p1:CumulativePhase><d2p1:Rank>118</d2p1:Rank><d2p1:StatsID>27</d2p1:StatsID><d2p1:ValueDecimal>36485.0000</d2p1:ValueDecimal><d2p1:ValueString>36485</d2p1:ValueString></d2p1:StatsItemDto></d2p1:StatsValues><d2p1:TeamID>43946</d2p1:TeamID></d2p1:PlayerStatsDto><d2p1:PlayerStatsDto><d2p1:ClubShirtName>MATUIDI</d2p1:ClubShirtName><d2p1:CommonName>MATUIDI</d2p1:CommonName><d2p1:PlayerID>358014</d2p1:PlayerID><d2p1:PlayerOfficialName>Blaise</d2p1:PlayerOfficialName><d2p1:PlayerOfficialSurname>MATUIDI</d2p1:PlayerOfficialSurname><d2p1:ShortName>MATUIDI</d2p1:ShortName><d2p1:StatsValues><d2p1:StatsItemDto><d2p1:CumulativePhase>0</d2p1:CumulativePhase><d2p1:Rank>38</d2p1:Rank><d2p1:StatsID>27</d2p1:StatsID><d2p1:ValueDecimal>50139.0000</d2p1:ValueDecimal><d2p1:ValueString>50139</d2p1:ValueString></d2p1:StatsItemDto></d2p1:StatsValues><d2p1:TeamID>43946</d2p1:TeamID></d2p1:PlayerStatsDto><d2p1:PlayerStatsDto><d2p1:ClubShirtName>GIROUD</d2p1:ClubShirtName><d2p1:CommonName>GIROUD</d2p1:CommonName><d2p1:PlayerID>358015</d2p1:PlayerID><d2p1:PlayerOfficialName>Olivier</d2p1:PlayerOfficialName><d2p1:PlayerOfficialSurname>GIROUD</d2p1:PlayerOfficialSurname><d2p1:ShortName>GIROUD</d2p1:ShortName><d2p1:StatsValues><d2p1:StatsItemDto><d2p1:CumulativePhase>0</d2p1:CumulativePhase><d2p1:Rank>309</d2p1:Rank><d2p1:StatsID>27</d2p1:StatsID><d2p1:ValueDecimal>20431.0000</d2p1:ValueDecimal><d2p1:ValueString>20431</d2p1:ValueString></d2p1:StatsItemDto></d2p1:StatsValues><d2p1:TeamID>43946</d2p1:TeamID></d2p1:PlayerStatsDto><d2p1:PlayerStatsDto><d2p1:ClubShirtName>VARANE</d2p1:ClubShirtName><d2p1:CommonName>VARANE</d2p1:CommonName><d2p1:PlayerID>359440</d2p1:PlayerID><d2p1:PlayerOfficialName>Raphael</d2p1:PlayerOfficialName><d2p1:PlayerOfficialSurname>VARANE</d2p1:PlayerOfficialSurname><d2p1:ShortName>VARANE</d2p1:ShortName><d2p1:StatsValues><d2p1:StatsItemDto><d2p1:CumulativePhase>0</d2p1:CumulativePhase><d2p1:Rank>79</d2p1:Rank><d2p1:StatsID>27</d2p1:StatsID><d2p1:ValueDecimal>41274.0000</d2p1:ValueDecimal><d2p1:ValueString>41274</d2p1:ValueString></d2p1:StatsItemDto></d2p1:StatsValues><d2p1:TeamID>43946</d2p1:TeamID></d2p1:PlayerStatsDto><d2p1:PlayerStatsDto><d2p1:ClubShirtName>POGBA</d2p1:ClubShirtName><d2p1:CommonName>POGBA</d2p1:CommonName><d2p1:PlayerID>367388</d2p1:PlayerID><d2p1:PlayerOfficialName>Paul</d2p1:PlayerOfficialName><d2p1:PlayerOfficialSurname>POGBA</d2p1:PlayerOfficialSurname><d2p1:ShortName>POGBA</d2p1:ShortName><d2p1:StatsValues><d2p1:StatsItemDto><d2p1:CumulativePhase>0</d2p1:CumulativePhase><d2p1:Rank>83</d2p1:Rank><d2p1:StatsID>27</d2p1:StatsID><d2p1:ValueDecimal>41192.0000</d2p1:ValueDecimal><d2p1:ValueString>41192</d2p1:ValueString></d2p1:StatsItemDto></d2p1:StatsValues><d2p1:TeamID>43946</d2p1:TeamID></d2p1:PlayerStatsDto><d2p1:PlayerStatsDto><d2p1:ClubShirtName>DIGNE</d2p1:ClubShirtName><d2p1:CommonName>DIGNE</d2p1:CommonName><d2p1:PlayerID>368860</d2p1:PlayerID><d2p1:PlayerOfficialName>Lucas</d2p1:PlayerOfficialName><d2p1:PlayerOfficialSurname>DIGNE</d2p1:PlayerOfficialSurname><d2p1:ShortName>DIGNE</d2p1:ShortName><d2p1:StatsValues><d2p1:StatsItemDto><d2p1:CumulativePhase>0</d2p1:CumulativePhase><d2p1:Rank>423</d2p1:Rank><d2p1:StatsID>27</d2p1:StatsID><d2p1:ValueDecimal>11165.0000</d2p1:ValueDecimal><d2p1:ValueString>11165</d2p1:ValueString></d2p1:StatsItemDto></d2p1:StatsValues><d2p1:TeamID>43946</d2p1:TeamID></d2p1:PlayerStatsDto><d2p1:PlayerStatsDto><d2p1:ClubShirtName>SCHNEIDERLIN</d2p1:ClubShirtName><d2p1:CommonName>Morgan SCHNEIDERLIN</d2p1:CommonName><d2p1:PlayerID>379995</d2p1:PlayerID><d2p1:PlayerOfficialName>Morgan</d2p1:PlayerOfficialName><d2p1:PlayerOfficialSurname>SCHNEIDERLIN</d2p1:PlayerOfficialSurname><d2p1:ShortName>SCHNEIDERLIN</d2p1:ShortName><d2p1:StatsValues><d2p1:StatsItemDto><d2p1:CumulativePhase>0</d2p1:CumulativePhase><d2p1:Rank>411</d2p1:Rank><d2p1:StatsID>27</d2p1:StatsID><d2p1:ValueDecimal>12228.0000</d2p1:ValueDecimal><d2p1:ValueString>12228</d2p1:ValueString></d2p1:StatsItemDto></d2p1:StatsValues><d2p1:TeamID>43946</d2p1:TeamID></d2p1:PlayerStatsDto><d2p1:PlayerStatsDto><d2p1:ClubShirtName>LANDREAU</d2p1:ClubShirtName><d2p1:CommonName>Mickael LANDREAU</d2p1:CommonName><d2p1:PlayerID>182021</d2p1:PlayerID><d2p1:PlayerOfficialName>Mickael</d2p1:PlayerOfficialName><d2p1:PlayerOfficialSurname>LANDREAU</d2p1:PlayerOfficialSurname><d2p1:ShortName>LANDREAU</d2p1:ShortName><d2p1:StatsValues /><d2p1:TeamID>43946</d2p1:TeamID></d2p1:PlayerStatsDto><d2p1:PlayerStatsDto><d2p1:ClubShirtName>MANGALA</d2p1:ClubShirtName><d2p1:CommonName>Eliaquim MANGALA</d2p1:CommonName><d2p1:PlayerID>319340</d2p1:PlayerID><d2p1:PlayerOfficialName>Eliaquim</d2p1:PlayerOfficialName><d2p1:PlayerOfficialSurname>MANGALA</d2p1:PlayerOfficialSurname><d2p1:ShortName>MANGALA</d2p1:ShortName><d2p1:StatsValues /><d2p1:TeamID>43946</d2p1:TeamID></d2p1:PlayerStatsDto><d2p1:PlayerStatsDto><d2p1:ClubShirtName>RUFFIER</d2p1:ClubShirtName><d2p1:CommonName>Stephane RUFFIER</d2p1:CommonName><d2p1:PlayerID>359448</d2p1:PlayerID><d2p1:PlayerOfficialName>Stephane</d2p1:PlayerOfficialName><d2p1:PlayerOfficialSurname>RUFFIER</d2p1:PlayerOfficialSurname><d2p1:ShortName>RUFFIER</d2p1:ShortName><d2p1:StatsValues /><d2p1:TeamID>43946</d2p1:TeamID></d2p1:PlayerStatsDto><d2p1:PlayerStatsDto><d2p1:ClubShirtName>CABELLA</d2p1:ClubShirtName><d2p1:CommonName>Remy CABELLA</d2p1:CommonName><d2p1:PlayerID>359454</d2p1:PlayerID><d2p1:PlayerOfficialName>Remy</d2p1:PlayerOfficialName><d2p1:PlayerOfficialSurname>CABELLA</d2p1:PlayerOfficialSurname><d2p1:ShortName>CABELLA</d2p1:ShortName><d2p1:StatsValues /><d2p1:TeamID>43946</d2p1:TeamID></d2p1:PlayerStatsDto><d2p1:PlayerStatsDto><d2p1:ClubShirtName>ESCOBER</d2p1:ClubShirtName><d2p1:CommonName>Donis ESCOBER</d2p1:CommonName><d2p1:PlayerID>213871</d2p1:PlayerID><d2p1:PlayerOfficialName>Donis</d2p1:PlayerOfficialName><d2p1:PlayerOfficialSurname>ESCOBER</d2p1:PlayerOfficialSurname><d2p1:ShortName>ESCOBER</d2p1:ShortName><d2p1:StatsValues /><d2p1:TeamID>43909</d2p1:TeamID></d2p1:PlayerStatsDto><d2p1:PlayerStatsDto><d2p1:ClubShirtName>DELGADO</d2p1:ClubShirtName><d2p1:CommonName>Edder DELGADO</d2p1:CommonName><d2p1:PlayerID>296312</d2p1:PlayerID><d2p1:PlayerOfficialName>Edder</d2p1:PlayerOfficialName><d2p1:PlayerOfficialSurname>DELGADO</d2p1:PlayerOfficialSurname><d2p1:ShortName>DELGADO</d2p1:ShortName><d2p1:StatsValues /><d2p1:TeamID>43909</d2p1:TeamID></d2p1:PlayerStatsDto><d2p1:PlayerStatsDto><d2p1:ClubShirtName>MONTES</d2p1:ClubShirtName><d2p1:CommonName>Juan MONTES</d2p1:CommonName><d2p1:PlayerID>365464</d2p1:PlayerID><d2p1:PlayerOfficialName>Juan</d2p1:PlayerOfficialName><d2p1:PlayerOfficialSurname>MONTES</d2p1:PlayerOfficialSurname><d2p1:ShortName>MONTES</d2p1:ShortName><d2p1:StatsValues /><d2p1:TeamID>43909</d2p1:TeamID></d2p1:PlayerStatsDto><d2p1:PlayerStatsDto><d2p1:ClubShirtName>R. MARTINEZ</d2p1:ClubShirtName><d2p1:CommonName>Rony MARTINEZ</d2p1:CommonName><d2p1:PlayerID>369990</d2p1:PlayerID><d2p1:PlayerOfficialName>Rony</d2p1:PlayerOfficialName><d2p1:PlayerOfficialSurname>MARTINEZ</d2p1:PlayerOfficialSurname><d2p1:ShortName>R. MARTINEZ</d2p1:ShortName><d2p1:StatsValues /><d2p1:TeamID>43909</d2p1:TeamID></d2p1:PlayerStatsDto><d2p1:PlayerStatsDto><d2p1:ClubShirtName>LOPEZ</d2p1:ClubShirtName><d2p1:CommonName>Luis LOPEZ</d2p1:CommonName><d2p1:PlayerID>380009</d2p1:PlayerID><d2p1:PlayerOfficialName>Luis</d2p1:PlayerOfficialName><d2p1:PlayerOfficialSurname>LOPEZ</d2p1:PlayerOfficialSurname><d2p1:ShortName>L. LOPEZ</d2p1:ShortName><d2p1:StatsValues /><d2p1:TeamID>43909</d2p1:TeamID></d2p1:PlayerStatsDto></d2p1:PlayerStats><d2p1:Season>2014</d2p1:Season><d2p1:StatsValues /><d2p1:TeamStats /><d2p1:UpdateTime><d2p1:Time>2014-06-12T21:54:40</d2p1:Time></d2p1:UpdateTime></CompetitionStatistics></GetCompetitionStatisticsByMatchResponse>